crl.rfcli-2.0.0-py3.7-nspkg.pth
crl/rfcli/__init__.py
crl/rfcli/_version.py
crl/rfcli/dumptrace.py
crl/rfcli/rfcli.py
crl.rfcli-2.0.0.dist-info/LICENSE
crl.rfcli-2.0.0.dist-info/METADATA
crl.rfcli-2.0.0.dist-info/WHEEL
crl.rfcli-2.0.0.dist-info/entry_points.txt
crl.rfcli-2.0.0.dist-info/namespace_packages.txt
crl.rfcli-2.0.0.dist-info/top_level.txt
crl.rfcli-2.0.0.dist-info/RECORD
