Metadata-Version: 2.1
Name: crl.rfcli
Version: 2.0.0
Summary: Robot Framework commands library
Home-page: https://github.com/nokia/crl-rfcli
Author: Krisztina Ylinen
Author-email: krisztina.ylinen@nokia.com
License: BSD-3-Clause
Keywords: robotframework
Classifier: Intended Audience :: Developers
Classifier: License :: OSI Approved :: BSD License
Classifier: Programming Language :: Python :: 3
Classifier: Programming Language :: Python :: 3.7
Classifier: Programming Language :: Python :: 3.8
Classifier: Programming Language :: Python :: 3.9
Classifier: Programming Language :: Python :: 3.10
Classifier: Programming Language :: Python :: 3.11
Classifier: Programming Language :: Python :: 3.12
Classifier: Framework :: Robot Framework :: Tool
Classifier: Topic :: Software Development
Requires-Python: >=3.7,<3.13
License-File: LICENSE
Requires-Dist: pyyaml
Requires-Dist: robotframework >=3.1
Requires-Dist: crl.threadverify
